MANIFEST.in
README.md
setup.py
riskmodels/__init__.py
riskmodels/bivariate.py
riskmodels/univariate.py
riskmodels.egg-info/PKG-INFO
riskmodels.egg-info/SOURCES.txt
riskmodels.egg-info/dependency_links.txt
riskmodels.egg-info/requires.txt
riskmodels.egg-info/top_level.txt
riskmodels/adequacy/__init__.py
riskmodels/adequacy/acg_models.py
riskmodels/adequacy/capacity_models.py
riskmodels/c/libbivarmargins.c
riskmodels/c/libbivarmargins.h
riskmodels/c/libtimedependence.c
riskmodels/c/libtimedependence.h
riskmodels/c/libunivarmargins.c
riskmodels/c/libunivarmargins.h
riskmodels/c/mtwist-1.5/mtwist.c
riskmodels/c/mtwist-1.5/mtwist.h
riskmodels/c/mtwist-1.5/randistrs.h
riskmodels/c_build/build_bivarmargins.py
riskmodels/c_build/build_timedependence.py
riskmodels/c_build/build_univarmargins.py
riskmodels/utils/__init__.py
riskmodels/utils/adequacy_interfaces.py
riskmodels/utils/map_reduce.py
riskmodels/utils/tmvn.py