Metadata-Version: 2.1
Name: riskmodels
Version: 2.2.0
Summary: Extreme value models for applications in energy procurement
Home-page: https://bitbucket.com/nestorsag/phd
Author: Nestor Sanchez
Author-email: nestor.sag@gmail.com
License: MIT
Platform: UNKNOWN
Classifier: Programming Language :: Python :: 3
Classifier: License :: OSI Approved :: MIT License
Classifier: Operating System :: OS Independent
Requires-Python: >=3.7
